odoo/addons/loyalty_initial_date_validity/README.rst
odoo/addons/loyalty_initial_date_validity/__init__.py
odoo/addons/loyalty_initial_date_validity/__manifest__.py
odoo/addons/loyalty_initial_date_validity/i18n/es.po
odoo/addons/loyalty_initial_date_validity/i18n/it.po
odoo/addons/loyalty_initial_date_validity/i18n/loyalty_initial_date_validity.pot
odoo/addons/loyalty_initial_date_validity/models/__init__.py
odoo/addons/loyalty_initial_date_validity/models/loyalty_program.py
odoo/addons/loyalty_initial_date_validity/readme/CONTEXT.rst
odoo/addons/loyalty_initial_date_validity/readme/CONTRIBUTORS.rst
odoo/addons/loyalty_initial_date_validity/readme/DESCRIPTION.rst
odoo/addons/loyalty_initial_date_validity/readme/ROADMAP.rst
odoo/addons/loyalty_initial_date_validity/readme/USAGE.rst
odoo/addons/loyalty_initial_date_validity/static/description/icon.png
odoo/addons/loyalty_initial_date_validity/static/description/index.html
odoo/addons/loyalty_initial_date_validity/tests/__init__.py
odoo/addons/loyalty_initial_date_validity/tests/test_loyalty_initial_date_validity.py
odoo/addons/loyalty_initial_date_validity/views/loyalty_program_views.xml
odoo_addon_loyalty_initial_date_validity-16.0.1.0.1.1.dist-info/METADATA
odoo_addon_loyalty_initial_date_validity-16.0.1.0.1.1.dist-info/WHEEL
odoo_addon_loyalty_initial_date_validity-16.0.1.0.1.1.dist-info/top_level.txt
odoo_addon_loyalty_initial_date_validity-16.0.1.0.1.1.dist-info/RECORD
